teslacam/__init__.py
teslacam/__main__.py
teslacam/arg_parser.py
teslacam/asyncio_subprocess.py
teslacam/constants.py
teslacam/custom_types.py
teslacam/extract.py
teslacam/layout.py
teslacam/time_duration.py
teslacam/unit.py
teslacam-1.0.3.dist-info/LICENSE
teslacam-1.0.3.dist-info/METADATA
teslacam-1.0.3.dist-info/WHEEL
teslacam-1.0.3.dist-info/top_level.txt
teslacam-1.0.3.dist-info/RECORD
