Metadata-Version: 2.1
Name: teslacam
Version: 1.0.3
Summary: Consolidate and format Tesla vehicle camera video data
Home-page: https://github.com/SillyGoat/teslacam
Author: SillyGoat
Author-email: fake.me.now.and.forever@gmail.com
License: UNKNOWN
Platform: UNKNOWN
Classifier: Programming Language :: Python :: 3
Classifier: License :: OSI Approved :: MIT License
Classifier: Operating System :: OS Independent
Requires-Python: >=3.8
License-File: LICENSE
